sema/__init__.py
sema/extract.py
sema/sema_cl_nav.py
sema/common/__init__.py
sema/common/check.py
sema/common/cli.py
sema/common/const.py
sema/common/get.py
sema/common/set.py
sema/manage_setting/__init__.py
sema/manage_setting/common.py
sema/manage_setting/manage_setting_cli.py
sema/manage_setting/manage_setting_gui.py
sema-0.1.3.dist-info/LICENSE
sema-0.1.3.dist-info/METADATA
sema-0.1.3.dist-info/WHEEL
sema-0.1.3.dist-info/entry_points.txt
sema-0.1.3.dist-info/top_level.txt
sema-0.1.3.dist-info/RECORD
