Metadata-Version: 2.1
Name: sema
Version: 0.1.3
Summary: Define easy to use and user friendly settings for your programs
Home-page: https://github.com/MoeinMavini/sema
Author: Moein Mavini
Author-email: moinmavini@gmail.com
License: MIT
Platform: UNKNOWN
Classifier: Programming Language :: Python :: 3
Classifier: License :: OSI Approved :: MIT License
Classifier: Operating System :: OS Independent
License-File: LICENSE
Requires-Dist: lxml
